microcosm_daemon/__init__.py
microcosm_daemon/api.py
microcosm_daemon/daemon.py
microcosm_daemon/error_policy.py
microcosm_daemon/health_reporter.py
microcosm_daemon/healthcheck_server.py
microcosm_daemon/reloader.py
microcosm_daemon/runner.py
microcosm_daemon/signal_handler.py
microcosm_daemon/sleep_policy.py
microcosm_daemon/standby.py
microcosm_daemon/state_machine.py
microcosm_daemon-3.0.0.dist-info/LICENSE
microcosm_daemon-3.0.0.dist-info/METADATA
microcosm_daemon-3.0.0.dist-info/WHEEL
microcosm_daemon-3.0.0.dist-info/entry_points.txt
microcosm_daemon-3.0.0.dist-info/top_level.txt
microcosm_daemon-3.0.0.dist-info/RECORD
